github_todoist_sync/__init__.py
github_todoist_sync/sync.py
github_todoist_sync-0.1.1.dist-info/METADATA
github_todoist_sync-0.1.1.dist-info/WHEEL
github_todoist_sync-0.1.1.dist-info/entry_points.txt
github_todoist_sync-0.1.1.dist-info/top_level.txt
github_todoist_sync-0.1.1.dist-info/RECORD
