Metadata-Version: 2.1
Name: github-todoist-sync
Version: 0.1.1
Summary: A tool to sync GitHub issues and PRs to Todoist tasks.
Author-email: Remco Sprooten <remco@sprooten.org>
License: MIT
Project-URL: Homepage, https://github.com/1337-42/Github2Todoist
Classifier: Development Status :: 4 - Beta
Classifier: License :: OSI Approved :: MIT License
Classifier: Programming Language :: Python :: 3.8
Classifier: Programming Language :: Python :: 3.9
Classifier: Programming Language :: Python :: 3.10
Classifier: Programming Language :: Python :: 3.11
Classifier: Programming Language :: Python :: 3.12
Classifier: Natural Language :: English
Requires-Python: >=3.6
Requires-Dist: PyGithub>=1.55
Requires-Dist: todoist-api-python>=1.3.0
